DB3.v
// Verilog Code for Divide-by-3 Finite State Machine

module DB3(clk, rst, in, out, state);
    input clk, rst, in;     // input controlling the operation
    output reg out;         // output of FSM
    output reg [1:0] state;        // state variable

    parameter A=2'b00,      //defining state parameters
              B=2'b01,
              C=2'b10,
              D=2'b11;

    always @ (posedge clk or negedge rst)       // condition for operation
            case(state)                         // switch case operation
                A: begin
                    out <= in ? 0 : 0;
                    state <= in ? B : A;
                   end

                B: begin
                    out <= in ? 0 : 0;
                    state <= in ? C : B;
                   end

                C: begin
                    out <= in ? 1 : 0;
                    state <= in ? D : C;
                   end

                D: begin
                    out <= in ? 0 : 0;
                    state <= in ? B : A;
                   end
                
                default: state = A;
            
            endcase
        
endmodule

DB3_test.v
// This is a TestBench File for Design Under Test

module DB3_test;
    reg clk, rst, in;
    wire out;
    wire [1:0] state;

    DB3 db3(clk, rst, in, out, state);             // module instantiated

    initial
        begin
            $dumpfile("DB3.vcd");           // output gets stored in this file
            $dumpvars(0, DB3_test);         // output parameters to be stored
            clk = 1'b0;                     // clock initialization
            rst = 1'b1; #4 rst = 1'b0;      // reset button initialization
        end

    always
        #5 clk = ~clk;                      // clock operation

    initial
        begin
            $display("Time\tState\tIn\tOut");
            $monitor("%g\t%b\t%b\t%b", $time, state, in, out);      // monitor output expression

            in = 1'b0;                                              // input starts here
            repeat(2)                                               // input variation loop
                begin
                    #20 in=1; #10 in=0; #10 in=1; #10 in=0;
                    #10 in=1; #10 in=0; #20 in=1; #20 in=0;
                    #10 in=1; #10 in=0; #10 in=1; #10 in=0;
                    #30 in=1; #10 in=0;
                end

            #10 $finish;                                            // end of test cases
        end

endmodule

DB3.vcd
$date
	Sat Jul 25 11:45:24 2020
$end
$version
	Icarus Verilog
$end
$timescale
	1s
$end
$scope module DB3_test $end
$var wire 1 ! out $end
$var wire 2 " state [1:0] $end
$var reg 1 # clk $end
$var reg 1 $ in $end
$var reg 1 % rst $end
$scope module db3 $end
$var wire 1 & clk $end
$var wire 1 ' in $end
$var wire 1 ( rst $end
$var reg 1 ) out $end
$var reg 2 * state [1:0] $end
$upscope $end
$upscope $end
$enddefinitions $end
#0
$dumpvars
bx *
x)
1(
0'
0&
1%
0$
0#
bx "
x!
$end
#4
b0 *
b0 "
0%
0(
#5
0)
0!
1#
1&
#10
0#
0&
#15
1#
1&
#20
0#
0&
1$
1'
#25
b1 *
b1 "
1#
1&
#30
0#
0&
0$
0'
#35
1#
1&
#40
0#
0&
1$
1'
#45
b10 *
b10 "
1#
1&
#50
0#
0&
0$
0'
#55
1#
1&
#60
0#
0&
1$
1'
#65
b11 *
b11 "
1)
1!
1#
1&
#70
0#
0&
0$
0'
#75
b0 *
b0 "
0)
0!
1#
1&
#80
0#
0&
#85
1#
1&
#90
0#
0&
1$
1'
#95
b1 *
b1 "
1#
1&
#100
0#
0&
#105
b10 *
b10 "
1#
1&
#110
0#
0&
0$
0'
#115
1#
1&
#120
0#
0&
1$
1'
#125
b11 *
b11 "
1)
1!
1#
1&
#130
0#
0&
0$
0'
#135
b0 *
b0 "
0)
0!
1#
1&
#140
0#
0&
1$
1'
#145
b1 *
b1 "
1#
1&
#150
0#
0&
0$
0'
#155
1#
1&
#160
0#
0&
#165
1#
1&
#170
0#
0&
#175
1#
1&
#180
0#
0&
1$
1'
#185
b10 *
b10 "
1#
1&
#190
0#
0&
0$
0'
#195
1#
1&
#200
0#
0&
#205
1#
1&
#210
0#
0&
1$
1'
#215
b11 *
b11 "
1)
1!
1#
1&
#220
0#
0&
0$
0'
#225
b0 *
b0 "
0)
0!
1#
1&
#230
0#
0&
1$
1'
#235
b1 *
b1 "
1#
1&
#240
0#
0&
0$
0'
#245
1#
1&
#250
0#
0&
1$
1'
#255
b10 *
b10 "
1#
1&
#260
0#
0&
0$
0'
#265
1#
1&
#270
0#
0&
#275
1#
1&
#280
0#
0&
1$
1'
#285
b11 *
b11 "
1)
1!
1#
1&
#290
0#
0&
#295
b1 *
b1 "
0)
0!
1#
1&
#300
0#
0&
0$
0'
#305
1#
1&
#310
0#
0&
1$
1'
#315
b10 *
b10 "
1#
1&
#320
0#
0&
0$
0'
#325
1#
1&
#330
0#
0&
1$
1'
#335
b11 *
b11 "
1)
1!
1#
1&
#340
0#
0&
0$
0'
#345
b0 *
b0 "
0)
0!
1#
1&
#350
0#
0&
#355
1#
1&
#360
0#
0&
#365
1#
1&
#370
0#
0&
1$
1'
#375
b1 *
b1 "
1#
1&
#380
0#
0&
0$
0'
